{
    "name" : "zenith",
    "environment" : {
        "sun_dir" : [ 0.54, -0.54, -0.54 ],
        "sun_col" : [ 1.0, 1.0, 1.0 ],
        "sun_softness" : 0.1,
        "env_col1" : [ 0.05, 0.075, 0.1 ],
        "env_map" : "env/stars",
        "env_map_pt" : "env/studio_small_03_2k.hdr"
    },
    "camera" : {
        "view_origin" : [ -35.785828, 66.084068, -74.004402 ],
        "view_dir" : [ 0.071197, -0.261730, 0.962485 ],
        "fwd_speed" : 0.5,
        "fov" : 75.0,
        "max_exposure" : 10.0
    },
    "meshes" : {
        "zenith" : {
            "mesh_file" : "new_test/zenith.mesh",
            "anims" : [
                "new_test/zenith_idle.anim"
            ]
        },
    },
    "decals" : {
    },
    "objects" : [
        {
            "name" : "zenith",
            "transform" : {
                "pos" : [ 0.0, 0.0, 0.0 ]
            },
            "drawable" : {
                "mesh" : "zenith"
            },
            "anim_state" : {}
        },
        {
            "transform" : {
                "pos" : [ 20.1092, 46.9592, 0.0 ],
                "rot" : [ 0.0, 0.0, 0.0 ]
            },
            "light" : {
                "offset" : [ 0.0, 0.0, 0.0 ],
                "color" : [ 400.0, 0.0, 0.0 ],
                "direction" : [ 0.0, -1.0, 0.0 ],
                "angle" : 180,
                "radius" : 0.1,
                "cast_shadow" : false
            }
        },
        {
            "transform" : {
                "pos" : [ 14.2193, 46.9592, -14.2193 ],
                "rot" : [ 0.0, 0.0, 0.0 ]
            },
            "light" : {
                "offset" : [ 0.0, 0.0, 0.0 ],
                "color" : [ 400.0, 0.0, 0.0 ],
                "direction" : [ 0.0, -1.0, 0.0 ],
                "angle" : 180,
                "radius" : 0.1,
                "cast_shadow" : false
            }
        },
        {
            "transform" : {
                "pos" : [ 0.0, 46.9592, -20.1092 ],
                "rot" : [ 0.0, 0.0, 0.0 ]
            },
            "light" : {
                "offset" : [ 0.0, 0.0, 0.0 ],
                "color" : [ 400.0, 0.0, 0.0 ],
                "direction" : [ 0.0, -1.0, 0.0 ],
                "angle" : 180,
                "radius" : 0.1,
                "cast_shadow" : false
            }
        },
    ]
}